ssb_altinn_form_tools/__init__.py
ssb_altinn_form_tools/__main__.py
ssb_altinn_form_tools/altinn_form_processor.py
ssb_altinn_form_tools/functions.py
ssb_altinn_form_tools/py.typed
ssb_altinn_form_tools-0.0.1.dist-info/METADATA
ssb_altinn_form_tools-0.0.1.dist-info/WHEEL
ssb_altinn_form_tools-0.0.1.dist-info/entry_points.txt
ssb_altinn_form_tools-0.0.1.dist-info/licenses/LICENSE
ssb_altinn_form_tools-0.0.1.dist-info/RECORD
