Metadata-Version: 2.4
Name: ssb-altinn-form-tools
Version: 0.0.1
Summary: SSB Altinn Form Tools
License-Expression: MIT
License-File: LICENSE
Author: Contact Person
Author-email: dor@ssb.no
Requires-Python: >=3.10,<4.0
Classifier: Development Status :: 3 - Alpha
Classifier: Programming Language :: Python :: 3
Classifier: Programming Language :: Python :: 3.10
Classifier: Programming Language :: Python :: 3.11
Classifier: Programming Language :: Python :: 3.12
Classifier: Programming Language :: Python :: 3.13
Classifier: Programming Language :: Python :: 3.14
Requires-Dist: click (>=8.0.1)
Project-URL: Changelog, https://github.com/statisticsnorway/ssb-altinn-form-tools/releases
Project-URL: Documentation, https://statisticsnorway.github.io/ssb-altinn-form-tools
Project-URL: Homepage, https://github.com/statisticsnorway/ssb-altinn-form-tools
Project-URL: Repository, https://github.com/statisticsnorway/ssb-altinn-form-tools
